ortec/scientific/benchmarks/loadbuilding/ApplicableConstraintsObjectives.py
ortec/scientific/benchmarks/loadbuilding/LoadbuildInstance.py
ortec/scientific/benchmarks/loadbuilding/LoadbuildSolution.py
ortec/scientific/benchmarks/loadbuilding/SolutionViewer.py
ortec/scientific/benchmarks/loadbuilding/__init__.py
ortec/scientific/benchmarks/loadbuilding/common/NgoiMatrix.py
ortec/scientific/benchmarks/loadbuilding/common/Requirements.py
ortec/scientific/benchmarks/loadbuilding/common/__init__.py
ortec/scientific/benchmarks/loadbuilding/common/utils.py
ortec/scientific/benchmarks/loadbuilding/common/constraints/AxleWeightConstraint.py
ortec/scientific/benchmarks/loadbuilding/common/constraints/ExactStackingConstraint.py
ortec/scientific/benchmarks/loadbuilding/common/constraints/MaximumWeightConstraint.py
ortec/scientific/benchmarks/loadbuilding/common/constraints/MustPlaceConstraint.py
ortec/scientific/benchmarks/loadbuilding/common/constraints/OrientationConstraint.py
ortec/scientific/benchmarks/loadbuilding/common/constraints/ReadableItemLabelConstraint.py
ortec/scientific/benchmarks/loadbuilding/common/constraints/SupportConstraint.py
ortec/scientific/benchmarks/loadbuilding/common/constraints/__init__.py
ortec/scientific/benchmarks/loadbuilding/common/objectives/AxleWeightObjective.py
ortec/scientific/benchmarks/loadbuilding/common/objectives/BoxCountObjective.py
ortec/scientific/benchmarks/loadbuilding/common/objectives/ContainerCountObjective.py
ortec/scientific/benchmarks/loadbuilding/common/objectives/FillRateObjectives.py
ortec/scientific/benchmarks/loadbuilding/common/objectives/ItemCountObjective.py
ortec/scientific/benchmarks/loadbuilding/common/objectives/PalletCountObjective.py
ortec/scientific/benchmarks/loadbuilding/common/objectives/__init__.py
ortec/scientific/benchmarks/loadbuilding/instance/ThreeDboxkind.py
ortec/scientific/benchmarks/loadbuilding/instance/ThreeDconstraint.py
ortec.scientific.benchmarks.loadbuilding-1.0.1.dist-info/METADATA
ortec.scientific.benchmarks.loadbuilding-1.0.1.dist-info/RECORD
ortec.scientific.benchmarks.loadbuilding-1.0.1.dist-info/WHEEL
ortec.scientific.benchmarks.loadbuilding-1.0.1.dist-info/entry_points.txt
ortec.scientific.benchmarks.loadbuilding-1.0.1.dist-info/top_level.txt
