Metadata-Version: 2.1
Name: ortec.scientific.benchmarks.loadbuilding
Version: 1.0.1
Summary: Tools for the working with the ORTEC loadbuilding benchmark problems
Home-page: https://benchmarks.ortec.com/Loadbuilding
Author: ORTECScientificBenchmarks
Author-email: benchmarks@ortec.com
License: MIT
Download-URL: https://github.com/ORTECScientificBenchmarks/ortec-scientific-benchmarks-loadbuilding/archive/master.zip
Project-URL: Source Code, http://github.com/ORTECScientificBenchmarks/ortec-scientific-benchmarks-loadbuilding
Project-URL: Package Index, https://pypi.org/project/ortec.scientific.benchmarks.loadbuilding/
Project-URL: ORTEC Benchmarks, https://benchmarks.ortec.com/
Project-URL: Documentation - Tools, https://benchmarks.ortec.com/Content/Loadbuilding/Documentation/Tools.pdf
Project-URL: Documentation - Instances, https://benchmarks.ortec.com/Content/Loadbuilding/Documentation/Instance.pdf
Project-URL: Documentation - Solutions, https://benchmarks.ortec.com/Content/Loadbuilding/Documentation/Solution.pdf
Keywords: loadbuilding scientific benchmarks ortec cutting packing
Platform: UNKNOWN
Classifier: Development Status :: 4 - Beta
Classifier: Intended Audience :: Science/Research
Classifier: License :: OSI Approved :: MIT License
Classifier: Programming Language :: Python :: 3
Classifier: Topic :: Scientific/Engineering
Requires-Python: ~=3.6
Requires-Dist: vpython
Requires-Dist: pyyaml (>=5.1)
